gatemate/__init__.py
gatemate-0.1.dist-info/METADATA
gatemate-0.1.dist-info/RECORD
gatemate-0.1.dist-info/WHEEL
gatemate-0.1.dist-info/top_level.txt
