Metadata-Version: 2.1
Name: gatemate
Version: 0.1
Summary: Gate answers are now just a command away.
Home-page: https://github.com/kb-studios/gatemate
Author: Kaushal Bhogale
Author-email: 2015kaushal.bhogale@ves.ac.in
License: MIT
Platform: UNKNOWN
Classifier: License :: OSI Approved :: MIT License
Classifier: Programming Language :: Python
Classifier: Programming Language :: Python :: 3
Classifier: Programming Language :: Python :: 3.6
Classifier: Programming Language :: Python :: Implementation :: CPython
Classifier: Programming Language :: Python :: Implementation :: PyPy
Requires-Python: >=3.5.0
